Metadata-Version: 1.0
Name: gtodo
Version: 0.2
Summary: Simple note taking CLI app
Home-page: UNKNOWN
Author: Samuel Ján Mucha
Author-email: samueljanmucha1@gmail.com
License: MIT
Platform: UNKNOWN
